modelradar/__init__.py
modelradar/evaluate/__init__.py
modelradar/evaluate/radar.py
modelradar/evaluate/rope.py
modelradar/utils/__init__.py
modelradar/utils/data.py
modelradar/visuals/__init__.py
modelradar/visuals/config.py
modelradar/visuals/plotter.py
modelradar-0.2.1.dist-info/METADATA
modelradar-0.2.1.dist-info/WHEEL
modelradar-0.2.1.dist-info/licenses/LICENSE
modelradar-0.2.1.dist-info/RECORD
