Metadata-Version: 2.4
Name: modelradar
Version: 0.2.1
Summary: Aspect-based Forecasting Accuracy
Project-URL: Homepage, https://github.com/vcerqueira/modelradar
Project-URL: Bug Tracker, https://github.com/vcerqueira/modelradar/issues
Author-email: Vitor Cerqueira <cerqueira.vitormanuel@gmail.com>
License-File: LICENSE
Keywords: Data Science,Evaluation,Forecasting,Machine Learning,Time Series
Classifier: License :: OSI Approved :: MIT License
Classifier: Operating System :: OS Independent
Classifier: Programming Language :: Python :: 3
Requires-Python: >=3.9
Requires-Dist: numpy==1.26.4
Requires-Dist: plotnine==0.14.5
Requires-Dist: utilsforecast==0.2.11
